bvareader/__init__.py
bvareader/commands.py
bvareader/helpers.py
bvareader/plotter.py
bvareader/preprocessing.py
bvareader/reader.py
tests/__init__.py
tests/conftest.py
tests/test_commands.py
tests/test_loading.py
bvareader-0.2.0.dist-info/METADATA
bvareader-0.2.0.dist-info/WHEEL
bvareader-0.2.0.dist-info/entry_points.txt
bvareader-0.2.0.dist-info/top_level.txt
bvareader-0.2.0.dist-info/RECORD
