Metadata-Version: 2.1
Name: bvareader
Version: 0.2.0
Summary: Package to read and process BVA data from LF Motol
Home-page: https://github.com/hejtmy/bva-reader
Author: Lukáš Hejtmy Hejtmánek
Author-email: hejtmy@gmail.com
License: UNKNOWN
Platform: UNKNOWN
Classifier: Programming Language :: Python :: 3
Classifier: License :: OSI Approved :: MIT License
Classifier: Operating System :: OS Independent
Requires-Dist: pandas
Requires-Dist: numpy (>=1.16.0)
Requires-Dist: matplotlib
Requires-Dist: Click (>=7.0)
